[
    {
        "id":1,
        "num":50,
        "beginTime":"24235353453453",
        "endTime":"123232456755",
        "articleTitlt":"河北省承德市委原书记郑雪碧被开除党籍和公职",
        "fenlei":"热点新闻",
        "laiyuan":"澎湃新闻网",
        "genxinTime":"2016年04月 7日 15:09",
        "cishu":"3434",
        "state":1,
        "jianlveTitle":"河北省承德市委原书",
        "ceshi":2,
        "feileilanmu":[
            {
            "lanmuId":2,
            "lanmuName":"新闻资讯",
            "xuanzhong":true
            },
            {
            "lanmuId":4,
            "lanmuName":"行业资讯",
            "xuanzhong":false
            },
            {
            "lanmuId":5,
            "lanmuName":"IT资讯",
            "xuanzhong":false
            },
            {
            "lanmuId":6,
            "lanmuName":"行业动态",
            "xuanzhong":false
            }
        ],
        "leixing":[
            {
                "leixingId":3,
                "leixingName":"帮助新闻",
                "leixingSel":true
            },
            {
                "leixingId":4,
                "leixingName":"有趣的事",
                "leixingSel":false
            },
            {
                "leixingId":5,
                "leixingName":"传奇故事",
                "leixingSel":false

            }
        ],
        "paixuzhi":"5",
        "guanjian":"新人,类型",
        "zaiyao":"河北省承德市委原书记郑",
        "zuozhe":"海明威",
        "isPinglun":true,
        "neirong":"河北省承德市委原书记郑雪碧被开除党籍和公职河北省承德市委原书记郑雪碧被开除党籍和公职河北省承德市委原书记郑雪碧被开除党籍和公职河北省承德市委原书记郑雪碧被开除党籍和公职河北省承德市委原书记郑雪碧被开除党籍和公职河北省承德市委原书记郑雪碧被开除党籍和公职河北省承德市委原书记郑雪碧被开除党籍和公职河北省承德市委原书记郑雪碧被开除党籍和公职河北省承德市委原书记郑雪碧被开除党籍和公职河北省承德市委原书记郑雪碧被开除党籍和公职河北省承德市委原书记郑雪碧被开除党籍和公职"

    },
    {
        "id":2,
        "num":20,
        "beginTime":"34734345634436",
        "endTime":"46856875685",
        "articleTitlt":"“一对一”访谈了200家典型企业，认真调查了解这些企业在稳增长、调结构的好经验、好做法；另一方面对3000家企业开展了问卷调查，了解企业主要困难和诉求。",
        "fenlei":"重点新闻",
        "laiyuan":"上海新闻网",
        "genxinTime":"2013年04月 6日 1:09",
        "cishu":"5844",
        "state":2,
        "jianlveTitle":"一对一”访谈了200家典型企业",
        "ceshi":1,
        "feileilanmu":[
            {
            "lanmuId":2,
            "lanmuName":"新闻资讯",
            "xuanzhong":false
            },
            {
            "lanmuId":4,
            "lanmuName":"行业资讯",
            "xuanzhong":false
            },
            {
            "lanmuId":5,
            "lanmuName":"IT资讯",
            "xuanzhong":true
            },
            {
            "lanmuId":6,
            "lanmuName":"行业动态",
            "xuanzhong":false
            }
        ],
        "leixing":[
            {
                "leixingId":3,
                "leixingName":"帮助新闻",
                "leixingSel":false
            },
            {
                "leixingId":4,
                "leixingName":"有趣的事",
                "leixingSel":false
            },
            {
                "leixingId":5,
                "leixingName":"传奇故事",
                "leixingSel":true

            }
        ],
        "paixuzhi":"5",
        "guanjian":"新人,类型",
        "zaiyao":"“一对一”访谈了200家典型企业",
        "zuozhe":"海明威",
        "isPinglun":true,
        "neirong":"“一对一”访谈了200家典型企业，认真调查了解这些企业在稳增长、调结构的好经验、好做法；另一方面对3000家企业开展了问卷调查，了解企业主要困难和诉求。“一对一”访谈了200家典型企业，认真调查了解这些企业在稳增长、调结构的好经验、好做法；另一方面对3000家企业开展了问卷调查，了解企业主要困难和诉求。"
    }
    ,
    {
        "id":3,
        "num":100,
        "beginTime":"3252356784545",
        "endTime":"065345522323234",
        "articleTitlt":"商务部近日下发通知，第119届广交会出口展区平均每个展位收费比第117届广交会降低4000元，降幅达到18%",
        "fenlei":"重点新闻",
        "laiyuan":"上海新闻网",
        "genxinTime":"2013年04月 6日 1:09",
        "cishu":"58",
        "state":3,
        "jianlveTitle":"商务部近日下发通知，第119届广交会出口展区平均每",
        "ceshi":3,
        "feileilanmu":[
            {
            "lanmuId":2,
            "lanmuName":"新闻资讯",
            "xuanzhong":false
            },
            {
            "lanmuId":4,
            "lanmuName":"行业资讯",
            "xuanzhong":false
            },
            {
            "lanmuId":5,
            "lanmuName":"IT资讯",
            "xuanzhong":false
            },
            {
            "lanmuId":6,
            "lanmuName":"行业动态",
            "xuanzhong":true
            }
        ],
        "leixing":[
            {
                "leixingId":3,
                "leixingName":"帮助新闻",
                "leixingSel":false
            },
            {
                "leixingId":4,
                "leixingName":"有趣的事",
                "leixingSel":false
            },
            {
                "leixingId":5,
                "leixingName":"传奇故事",
                "leixingSel":true

            }
        ],
        "paixuzhi":"5",
        "guanjian":"新人,类型",
        "zaiyao":"商务部近日下发通知，",
        "zuozhe":"海明威",
        "isPinglun":true,
        "neirong":"商务部近日下发通知，第119届广交会出口展区平均每个展位收费比第117届广交会降低4000元，降幅达到18商务部近日下发通知，第119届广交会出口展区平均每个展位收费比第117届广交会降低4000元，降幅达到18商务部近日下发通知，第119届广交会出口展区平均每个展位收费比第117届广交会降低4000元，降幅达到18商务部近日下发通知，第119届广交会出口展区平均每个展位收费比第117届广交会降低4000元，降幅达到18商务部近日下发通知，第119届广交会出口展区平均每个展位收费比第117届广交会降低4000元，降幅达到18商务部近日下发通知，第119届广交会出口展区平均每个展位收费比第117届广交会降低4000元，降幅达到18商务部近日下发通知，第119届广交会出口展区平均每个展位收费比第117届广交会降低4000元，降幅达到18商务部近日下发通知，第119届广交会出口展区平均每个展位收费比第117届广交会降低4000元，降幅达到18商务部近日下发通知，第119届广交会出口展区平均每个展位收费比第117届广交会降低4000元，降幅达到18商务部近日下发通知，第119届广交会出口展区平均每个展位收费比第117届广交会降低4000元，降幅达到18"
    }
    ,
    {
        "id":4,
        "num":80,
        "beginTime":"1231423535356",
        "endTime":"464334567543",
        "articleTitlt":"两母子在迪士尼乐园中疯玩12个小时，血拼一天甚至忘记了吃饭。汪东城在微博中PO出照片，他和妈妈在迪斯尼中购买的动漫周边产品堆满了整个床，“战绩”惊人。除了血拼、逛景点之外，汪东城更期待能带妈妈看到樱花开满的景象，从他PO出的照片看，虽然有少数樱花盛开，但还没有到漫天樱花",
        "fenlei":"好看新闻",
        "laiyuan":"安徽新闻网",
        "genxinTime":"2016年04月 9日 1:09",
        "cishu":"5555",
        "state":4,
        "jianlveTitle":"两母子在迪士尼乐园中疯玩12个小时，血拼一天甚至忘记了吃饭。汪东城在微博中PO出照片",
        "ceshi":4,
        "feileilanmu":[
            {
            "lanmuId":2,
            "lanmuName":"新闻资讯",
            "xuanzhong":false
            },
            {
            "lanmuId":4,
            "lanmuName":"行业资讯",
            "xuanzhong":true
            },
            {
            "lanmuId":5,
            "lanmuName":"IT资讯",
            "xuanzhong":false
            },
            {
            "lanmuId":6,
            "lanmuName":"行业动态",
            "xuanzhong":false
            }
        ],
        "leixing":[
            {
                "leixingId":3,
                "leixingName":"帮助新闻",
                "leixingSel":false
            },
            {
                "leixingId":4,
                "leixingName":"有趣的事",
                "leixingSel":false
            },
            {
                "leixingId":5,
                "leixingName":"传奇故事",
                "leixingSel":true

            }
        ],
        "paixuzhi":"5",
        "guanjian":"新人,类型",
        "zaiyao":"两母子在迪士尼乐园中疯玩12个",
        "zuozhe":"姜西",
        "isPinglun":false,
        "neirong":"两母子在迪士尼乐园中疯玩12个小时，血拼一天甚至忘记了吃饭。汪东城在微博中PO出照片，他和妈妈在迪斯尼中购买的动漫周边产品堆满了整个床，“战绩”惊人。除了血拼、逛景点之外，汪东城更期待能带妈妈看到樱花开满的景象，从他PO出的照片看，虽然有少数樱花盛开，但还没有到漫天樱花两母子在迪士尼乐园中疯玩12个小时，血拼一天甚至忘记了吃饭。汪东城在微博中PO出照片，他和妈妈在迪斯尼中购买的动漫周边产品堆满了整个床，“战绩”惊人。除了血拼、逛景点之外，汪东城更期待能带妈妈看到樱花开满的景象，从他PO出的照片看，虽然有少数樱花盛开，但还没有到漫天樱花两母子在迪士尼乐园中疯玩12个小时，血拼一天甚至忘记了吃饭。汪东城在微博中PO出照片，他和妈妈在迪斯尼中购买的动漫周边产品堆满了整个床，“战绩”惊人。除了血拼、逛景点之外，汪东城更期待能带妈妈看到樱花开满的景象，从他PO出的照片看，虽然有少数樱花盛开，但还没有到漫天樱花两母子在迪士尼乐园中疯玩12个小时，血拼一天甚至忘记了吃饭。汪东城在微博中PO出照片，他和妈妈在迪斯尼中购买的动漫周边产品堆满了整个床，“战绩”惊人。除了血拼、逛景点之外，汪东城更期待能带妈妈看到樱花开满的景象，从他PO出的照片看，虽然有少数樱花盛开，但还没有到漫天樱花两母子在迪士尼乐园中疯玩12个小时，血拼一天甚至忘记了吃饭。汪东城在微博中PO出照片，他和妈妈在迪斯尼中购买的动漫周边产品堆满了整个床，“战绩”惊人。除了血拼、逛景点之外，汪东城更期待能带妈妈看到樱花开满的景象，从他PO出的照片看，虽然有少数樱花盛开，但还没有到漫天樱花"
    }
]



